README.md
setup.py
src/emqx/__init__.py
src/emqx/exproto/__init__.py
src/emqx/exproto/abstract_handler.py
src/emqx/exproto/client_info.py
src/emqx/exproto/connection.py
src/emqx/exproto/core.py
src/emqx/exproto/driver.py
src/emqx/exproto/ex_proto.py
src/emqx/exproto/message.py
src/emqx/exproto/sock_type.py
src/emqx/exproto/until.py
src/emqx_exproto_sdk.egg-info/PKG-INFO
src/emqx_exproto_sdk.egg-info/SOURCES.txt
src/emqx_exproto_sdk.egg-info/dependency_links.txt
src/emqx_exproto_sdk.egg-info/not-zip-safe
src/emqx_exproto_sdk.egg-info/top_level.txt