Metadata-Version: 1.0
Name: emqx-exproto-sdk
Version: 0.1.4
Summary: The Python SDK for emqx-exproto
Home-page: https://github.com/emqx/emqx-exproto-python-sdk
Author: adek06
Author-email: adek06@outlook.com
License: UNKNOWN
Keywords: emqx
Platform: UNKNOWN
